contextual/__init__.py
contextual/_base_client.py
contextual/_client.py
contextual/_compat.py
contextual/_constants.py
contextual/_exceptions.py
contextual/_files.py
contextual/_models.py
contextual/_qs.py
contextual/_resource.py
contextual/_response.py
contextual/_streaming.py
contextual/_types.py
contextual/_version.py
contextual/pagination.py
contextual/py.typed
contextual/_utils/__init__.py
contextual/_utils/_compat.py
contextual/_utils/_datetime_parse.py
contextual/_utils/_logs.py
contextual/_utils/_proxy.py
contextual/_utils/_reflection.py
contextual/_utils/_resources_proxy.py
contextual/_utils/_streams.py
contextual/_utils/_sync.py
contextual/_utils/_transform.py
contextual/_utils/_typing.py
contextual/_utils/_utils.py
contextual/lib/.keep
contextual/resources/__init__.py
contextual/resources/generate.py
contextual/resources/lmunit.py
contextual/resources/parse.py
contextual/resources/rerank.py
contextual/resources/users.py
contextual/resources/agents/__init__.py
contextual/resources/agents/agents.py
contextual/resources/agents/query.py
contextual/resources/datastores/__init__.py
contextual/resources/datastores/contents.py
contextual/resources/datastores/datastores.py
contextual/resources/datastores/documents.py
contextual/types/__init__.py
contextual/types/agent.py
contextual/types/agent_configs.py
contextual/types/agent_configs_param.py
contextual/types/agent_create_params.py
contextual/types/agent_list_params.py
contextual/types/agent_metadata.py
contextual/types/agent_metadata_response.py
contextual/types/agent_update_params.py
contextual/types/create_agent_output.py
contextual/types/create_datastore_response.py
contextual/types/datastore.py
contextual/types/datastore_create_params.py
contextual/types/datastore_list_params.py
contextual/types/datastore_metadata.py
contextual/types/datastore_update_params.py
contextual/types/datastore_update_response.py
contextual/types/filter_and_rerank_config.py
contextual/types/filter_and_rerank_config_param.py
contextual_client-0.10.0.dist-info/METADATA
contextual_client-0.10.0.dist-info/WHEEL
contextual_client-0.10.0.dist-info/licenses/LICENSE
contextual_client-0.10.0.dist-info/RECORD
